{"item.armor.equip_chain":{"sounds":["item/armor/equip_chain1","item/armor/equip_chain2","item/armor/equip_chain3","item/armor/equip_chain4","item/armor/equip_chain5","item/armor/equip_chain6"],"subtitle":"subtitles.item.armor.equip_chain"},"item.armor.equip_diamond":{"sounds":["item/armor/equip_diamond1","item/armor/equip_diamond2","item/armor/equip_diamond3","item/armor/equip_diamond4","item/armor/equip_diamond5","item/armor/equip_diamond6"],"subtitle":"subtitles.item.armor.equip_diamond"},"item.armor.equip_elytra":{"sounds":["item/armor/equip_leather1","item/armor/equip_leather2","item/armor/equip_leather3","item/armor/equip_leather4","item/armor/equip_leather5","item/armor/equip_leather6"],"subtitle":"subtitles.item.armor.equip_elytra"},"item.armor.equip_generic":{"sounds":["item/armor/equip_generic1","item/armor/equip_generic2","item/armor/equip_generic3","item/armor/equip_generic4","item/armor/equip_generic5","item/armor/equip_generic6"],"subtitle":"subtitles.item.armor.equip"},"item.armor.equip_gold":{"sounds":["item/armor/equip_gold1","item/armor/equip_gold2","item/armor/equip_gold3","item/armor/equip_gold4","item/armor/equip_gold5","item/armor/equip_gold6"],"subtitle":"subtitles.item.armor.equip_gold"},"item.armor.equip_iron":{"sounds":["item/armor/equip_iron1","item/armor/equip_iron2","item/armor/equip_iron3","item/armor/equip_iron4","item/armor/equip_iron5","item/armor/equip_iron6"],"subtitle":"subtitles.item.armor.equip_iron"},"item.armor.equip_leather":{"sounds":["item/armor/equip_leather1","item/armor/equip_leather2","item/armor/equip_leather3","item/armor/equip_leather4","item/armor/equip_leather5","item/armor/equip_leather6"],"subtitle":"subtitles.item.armor.equip_leather"},"item.armor.equip_netherite":{"sounds":[{"name":"item/armor/equip_netherite1","volume":0.8},{"name":"item/armor/equip_netherite1","pitch":0.9,"volume":0.8},{"name":"item/armor/equip_netherite2","volume":0.8},{"name":"item/armor/equip_netherite2","pitch":0.9,"volume":0.8},{"name":"item/armor/equip_netherite3","volume":0.8},{"name":"item/armor/equip_netherite3","pitch":0.9,"volume":0.8},{"name":"item/armor/equip_netherite4","volume":0.8},{"name":"item/armor/equip_netherite4","pitch":0.9,"volume":0.8}],"subtitle":"subtitles.item.armor.equip_netherite"},"item.armor.equip_turtle":{"sounds":["mob/turtle/armor",{"name":"mob/turtle/armor","pitch":0.85},{"name":"mob/turtle/armor","pitch":1.1}],"subtitle":"subtitles.item.armor.equip_turtle"},"block.wood.break":{"sounds":["dig/wood1","dig/wood2","dig/wood3","dig/wood4"],"subtitle":"subtitles.block.generic.break"},"block.wood.hit":{"sounds":["step/wood1","step/wood2","step/wood3","step/wood4","step/wood5","step/wood6"],"subtitle":"subtitles.block.generic.hit"},"block.wood.step":{"sounds":["step/wood1","step/wood2","step/wood3","step/wood4","step/wood5","step/wood6"],"subtitle":"subtitles.block.generic.footsteps"},"block.wood.fall":{"sounds":["step/wood1","step/wood2","step/wood3","step/wood4","step/wood5","step/wood6"]},"block.stone.break":{"sounds":["dig/stone1","dig/stone2","dig/stone3","dig/stone4"],"subtitle":"subtitles.block.generic.break"},"block.stone.hit":{"sounds":["step/stone1","step/stone2","step/stone3","step/stone4","step/stone5","step/stone6"],"subtitle":"subtitles.block.generic.hit"},"block.stone.step":{"sounds":["step/stone1","step/stone2","step/stone3","step/stone4","step/stone5","step/stone6"],"subtitle":"subtitles.block.generic.footsteps"},"block.stone.fall":{"sounds":["step/stone1","step/stone2","step/stone3","step/stone4","step/stone5","step/stone6"]}}